[
  {
    "name": "Student Government Association",
    "description": "An organization for representing students",
    "id": "5a8d27de-a51a-486f-99dd-a3227f12f77b"
  },
  {
    "name": "Computer Science Club",
    "description": "An organization for students interested in CS",
    "id": "99095cba-a2a0-4414-8337-309937f174c6"
  },
  {
    "name": "Ultimate Frisbee Club",
    "description": "An organization for students interested in ultimate frisbee",
    "id": "612c62ac-de0c-4233-a99e-10a4d336dd81"
  },
  {
    "name": "Underwater Basket Weaving Club",
    "description": "An organization for students interested in underwaster basket weaving",
    "id": "5397e314-8929-44d0-ad04-ba392050dea0"
  },
  {
    "name": "Data Science Club",
    "description": "An organization for students interested in Data Science",
    "id": "fb10771e-4fd1-454f-a016-32910c13205b"
  },
  {
    "name": "Fine Arts Appreciation Organization",
    "description": "An organization for the appreciation of fine arts",
    "id": "0891c055-b826-4103-85fb-61e7b8a60760"
  },
  {
    "name": "Harry Potter Club",
    "description": "A club for fans of Harry Potter",
    "id": "2a5a6285-1d8e-40ed-bec4-28eec1e23c33"
  },
  {
    "name": "Honors Society",
    "description": "_The_ Honors Society",
    "id": "99a7a946-9e57-48e8-b76e-c5be6aa52a69"
  },
  {
    "name": "Craft Brewers Org",
    "description": "An organization for craft brewers",
    "id": "b2c8aa4e-e794-4767-8849-b3356794ecc9"
  },
  {
    "name": "Curling Team",
    "description": "The University Curling team",
    "id": "4b6f7124-f3e8-4c4e-8023-fb5fa09bca6e"
  },
  {
    "name": "Alpha Kappa Lambda",
    "description": "AKL Social Fraternity",
    "id": "2fbfb44b-51a0-4283-9d31-39066f734ffc"
  },
  {
    "name": "Collegiate Entrenprenuership Organization",
    "description": "A club for students interested in business",
    "id": "0ced3396-b933-466f-9886-8e64724b3120"
  },
  {
    "name": "Whale Watchers United",
    "description": "Student org for whale watchers",
    "id": "0a181f1c-c2b2-4046-865f-350571e71d52"
  },
  {
    "name": "Fight Club",
    "description": "We don't talk about it",
    "id": "076aff7f-bf8c-447f-8576-bcf8e3359f25"
  },
  {
    "name": "Fine Wine & Cheese Guild",
    "description": "For lovers of fine wine and cheese",
    "id": "1a5ed000-fdb8-42ec-9a08-709114592c57"
  },
  {
    "name": "Student Coffee Consortium",
    "description": "Coffee snobs, mostly.",
    "id": "11b28f55-acc7-41f7-a069-9151fd618c45"
  },
  {
    "name": "Accounting Club",
    "description": "We take credit or debit",
    "id": "fd7fadf3-cc07-4b4f-9a40-41f5b05fb751"
  },
  {
    "name": "Alpha Sigma Tau",
    "description": "AST Social Soriety",
    "id": "fa84b0a9-abb4-4e58-888e-136e611cc1b4"
  },
  {
    "name": "The 19th Org",
    "description": "Super Secret",
    "id": "8dbb3d99-a2bc-4068-8f9a-0cdb3bdc7fc7"
  },
  {
    "name": "Polly-Sci Club",
    "description": "Political Science Club",
    "id": "3d3d5760-183a-405c-9c14-4c3c094dc94d"
  }
]